swannotificationsservice/__init__.py
swannotificationsservice/__main__.py
swannotificationsservice/_version.py
swannotificationsservice/app.py
swannotificationsservice/service.py
swannotificationsservice-1.0.1.dist-info/METADATA
swannotificationsservice-1.0.1.dist-info/WHEEL
swannotificationsservice-1.0.1.dist-info/entry_points.txt
swannotificationsservice-1.0.1.dist-info/top_level.txt
swannotificationsservice-1.0.1.dist-info/RECORD
