Metadata-Version: 2.1
Name: swannotificationsservice
Version: 1.0.1
Summary: JupyterHub service to expose notifications for Jupyter
Home-page: https://github.com/swan-cern/jupyterhub-extensions
Author: SWAN Admins
License: AGPL-3.0
Keywords: JupyterHub,SWAN,CERN
Platform: Linux
Platform: Mac OS X
Classifier: License :: OSI Approved :: GNU Affero General Public License v3
Classifier: Intended Audience :: Developers
Classifier: Intended Audience :: System Administrators
Classifier: Intended Audience :: Science/Research
Classifier: Programming Language :: Python
Classifier: Programming Language :: Python :: 3
Requires-Dist: jupyterhub~=4.1.6
Requires-Dist: kubernetes~=22.0
